radarx/__init__.py
radarx/accessors.py
radarx/radarx.py
radarx/utils.py
radarx/version.py
radarx/fundamentals/__init__.py
radarx/fundamentals/attenuation.py
radarx/fundamentals/beam.py
radarx/fundamentals/common.py
radarx/fundamentals/constants.py
radarx/fundamentals/doppler.py
radarx/fundamentals/geometry.py
radarx/fundamentals/power.py
radarx/fundamentals/principles.py
radarx/fundamentals/reflectivity.py
radarx/fundamentals/scattering.py
radarx/fundamentals/system.py
radarx/fundamentals/timing.py
radarx/fundamentals/variables.py
radarx/grid/__init__.py
radarx/grid/grid.py
radarx/io/__init__.py
radarx/io/aws_data.py
radarx/io/imd.py
radarx/testing/__init__.py
radarx/testing/test_data_imd.py
radarx/vis/__init__.py
radarx/vis/maxcappi.py
radarx-0.2.5.dist-info/licenses/AUTHORS.md
radarx-0.2.5.dist-info/licenses/LICENSE
radarx-0.2.5.dist-info/METADATA
radarx-0.2.5.dist-info/WHEEL
radarx-0.2.5.dist-info/top_level.txt
radarx-0.2.5.dist-info/RECORD
